MANIFEST.in
index.html
setup.py
bootstrap/css/bootstrap-theme.css
bootstrap/css/bootstrap-theme.css.map
bootstrap/css/bootstrap-theme.min.css
bootstrap/css/bootstrap-theme.min.css.map
bootstrap/css/bootstrap.css
bootstrap/css/bootstrap.css.map
bootstrap/css/bootstrap.min.css
bootstrap/css/bootstrap.min.css.map
bootstrap/fonts/glyphicons-halflings-regular.eot
bootstrap/fonts/glyphicons-halflings-regular.svg
bootstrap/fonts/glyphicons-halflings-regular.ttf
bootstrap/fonts/glyphicons-halflings-regular.woff
bootstrap/fonts/glyphicons-halflings-regular.woff2
bootstrap/js/bootstrap.js
bootstrap/js/bootstrap.min.js
bootstrap/js/npm.js
css/main.css
galfect/__init__.py
galfect/cmdline.py
galfect.egg-info/PKG-INFO
galfect.egg-info/SOURCES.txt
galfect.egg-info/dependency_links.txt
galfect.egg-info/entry_points.txt
galfect.egg-info/top_level.txt
galfect/initialize/__init__.py