Metadata-Version: 1.0
Name: galfect
Version: 0.3.0
Summary: Converting drama text to html pages
Home-page: http://liriansu.com
Author: Lirian Su
Author-email: liriansu@gmail.com
License: Creative Commons Attribution-Noncommercial-Share Alike license
Platform: UNKNOWN
